main.py
crypto_feargreed_mcp-0.1.0.dist-info/licenses/LICENSE
crypto_feargreed_mcp-0.1.0.dist-info/METADATA
crypto_feargreed_mcp-0.1.0.dist-info/WHEEL
crypto_feargreed_mcp-0.1.0.dist-info/top_level.txt
crypto_feargreed_mcp-0.1.0.dist-info/RECORD
